[
    {
        "id": 1,
        "post": {
            "votes": "10",
            "link": "/l/e66746ac86",
            "name": "Punchclock",
            "tagline": "Checkin to work automatically with iBeacons",
            "ph_url": "posts/punchclock",
            "comments": "2"
        },
        "user": {
            "id": "mccannatron",
            "image": "http://res.cloudinary.com/product-hunt/image/twitter_name/w_150,h_150/mccannatron.jpg",
            "twitter": "mccannatron",
            "name": "Chris McCann",
            "tagline": "Community at Greylock Partners"
        }
    },
    {
        "id": 2,
        "post": {
            "votes": "8",
            "link": "/l/8e177eb327",
            "name": "Ghosted",
            "tagline": "like wordpress.com for the Ghost Blog platform",
            "ph_url": "posts/ghosted",
            "comments": "2"
        },
        "user": {
            "id": "_jacksmith",
            "image": "http://res.cloudinary.com/product-hunt/image/twitter_name/w_150,h_150/_jacksmith.jpg",
            "twitter": "_jacksmith",
            "name": "Jack Smith",
            "tagline": "Co-Founded Vungle &amp; Shyp - Advisor at Coin, Survios &amp; Trak"
        }
    },
    {
        "id": 3,
        "post": {
            "votes": "8",
            "link": "/l/6bc2f2ba4a",
            "name": "Motif ",
            "tagline": "Stop picking stocks. Invest in Ideas.",
            "ph_url": "posts/motif",
            "comments": "1 comment"
        },
        "user": {
            "id": "ShaanVP",
            "image": "http://res.cloudinary.com/product-hunt/image/twitter_name/w_150,h_150/ShaanVP.jpg",
            "twitter": "ShaanVP",
            "name": "Shaan Puri",
            "tagline": "ceo, Monkey Inferno"
        }
    },
    {
        "id": 4,
        "post": {
            "votes": "4",
            "link": "/l/39fbf67a4d",
            "name": "Deez",
            "tagline": "Start monitoring your domains now",
            "ph_url": "posts/deez",
            "comments": "1 comment"
        },
        "user": {
            "id": "brnt",
            "image": "http://res.cloudinary.com/product-hunt/image/twitter_name/w_150,h_150/brnt.jpg",
            "twitter": "brnt",
            "name": "Bernat Fages",
            "tagline": "calloud.com creator &amp; founder"
        }
    },
    {
        "id": 5,
        "post": {
            "votes": "2",
            "link": "/l/44b1a9ccae",
            "name": "Activity Walls",
            "tagline": "Twitter &amp; Instagram displays for events in under 30 secs",
            "ph_url": "posts/activity-walls",
            "comments": "1 comment"
        },
        "user": {
            "id": "toddg777",
            "image": "https://pbs.twimg.com/profile_images/378800000324080808/451674c425fe5d8a7013fb959bbfcf7a.png",
            "twitter": "toddg777",
            "name": "Todd Goldberg",
            "tagline": "Eventjoy Co-founder"
        }
    },
    {
        "id": 6,
        "post": {
            "votes": "1",
            "link": "/l/ff50d39b07",
            "name": "Slate",
            "tagline": "Making Spreadsheets Understandable. ",
            "ph_url": "posts/slate",
            "comments": "1 comment"
        },
        "user": {
            "id": "kwdinc",
            "image": "http://res.cloudinary.com/product-hunt/image/twitter_name/w_150,h_150/kwdinc.jpg",
            "twitter": "kwdinc",
            "name": "Kevin William David",
            "tagline": "Co-Founder,WalletKit"
        }
    }
]