[
    {
        "id": 1,
        "post": {
            "votes": "46",
            "link": "/l/d288f86c7a",
            "name": "StartUp ",
            "tagline": "Alex Blumberg&#39;s (Planet Money/NPR) new startup podcast.",
            "ph_url": "posts/startup",
            "comments": "8"
        },
        "user": {
            "id": "brentmulligan",
            "image": "https://pbs.twimg.com/profile_images/2223243330/301941_740967867706_41503020_35880455_629628037_n_normal.jpg",
            "twitter": "brentmulligan",
            "name": "Brent Mulligan",
            "tagline": "Founder"
        }
    },
    {
        "id": 2,
        "post": {
            "votes": "20",
            "link": "/l/b9971e9fb5",
            "name": "Karma by Aleph",
            "tagline": "Place for entrepreneurs to help each other",
            "ph_url": "posts/karma-by-aleph",
            "comments": "0"
        },
        "user": {
            "id": "benln",
            "image": "https://pbs.twimg.com/profile_images/3785988126/e78d1f6c7bb2a4f53fd0bfe51fb31d7c_normal.png",
            "twitter": "benln",
            "name": "Ben Lang",
            "tagline": "Founder, Mapped In Israel"
        }
    },
    {
        "id": 3,
        "post": {
            "votes": "5",
            "link": "/l/304531885d",
            "name": "TestFlight (iOS app)",
            "tagline": "Beta testing is easier than ever",
            "ph_url": "posts/testflight-ios-app",
            "comments": "1"
        },
        "user": {
            "id": "ikar1m",
            "image": "http://pbs.twimg.com/profile_images/481918083037396992/qM82_iwM_normal.jpeg",
            "twitter": "ikar1m",
            "name": "Karim",
            "tagline": "Mobile &amp; Web UI/UX designer &amp; developer"
        }
    },
    {
        "id": 4,
        "post": {
            "votes": "8",
            "link": "/l/e9d42d3ada",
            "name": "The Met",
            "tagline": "Official app of The Metropolitan Museum of Art",
            "ph_url": "posts/the-met",
            "comments": "1"
        },
        "user": {
            "id": "nikkielizdemere",
            "image": "https://pbs.twimg.com/profile_images/462976562275430400/7n6vDLrd_normal.jpeg",
            "twitter": "nikkielizdemere",
            "name": "Nichole Elizabeth",
            "tagline": "Community at Product Hunt"
        }
    },
    {
        "id": 5,
        "post": {
            "votes": "6",
            "link": "/l/df4dd6b9b6",
            "name": "Clyp",
            "tagline": "Sounds Worth Sharing",
            "ph_url": "posts/clyp",
            "comments": "0"
        },
        "user": {
            "id": "WhatTheFerguson",
            "image": "https://pbs.twimg.com/profile_images/2819361888/a7efdc60f715c78167f9b6f460f5c061_normal.png",
            "twitter": "WhatTheFerguson",
            "name": "Tyson Ferguson",
            "tagline": "Co-Founder, Designer at Clyp"
        }
    },
    {
        "id": 6,
        "post": {
            "votes": "4",
            "link": "/l/be4214788e",
            "name": "NASA App",
            "tagline": "Showcases a huge collection of the latest NASA content",
            "ph_url": "posts/nasa-app",
            "comments": "1"
        },
        "user": {
            "id": "nikkielizdemere",
            "image": "https://pbs.twimg.com/profile_images/462976562275430400/7n6vDLrd_normal.jpeg",
            "twitter": "nikkielizdemere",
            "name": "Nichole Elizabeth",
            "tagline": "Community at Product Hunt"
        }
    }
]