[
    {
        "id": 1,
        "post": {
            "votes": "140",
            "link": "/l/3cf5ec1224",
            "name": "readme",
            "tagline": "Beautiful Documentation Made Easy",
            "ph_url": "posts/readme-2",
            "comments": "13"
        },
        "user": {
            "id": "_jacksmith",
            "image": "https://pbs.twimg.com/profile_images/505259361157910529/022ehIu4_normal.png",
            "twitter": "_jacksmith",
            "name": "Jack Smith",
            "tagline": "Co-Founded Vungle - Advisor to Coin"
        }
    },
    {
        "id": 2,
        "post": {
            "votes": "63",
            "link": "/l/b7b5fbdf47",
            "name": "StartupClass.co",
            "tagline": "YC&#39;s How to Start a Startup packaged as an online course",
            "ph_url": "posts/startupclass-co",
            "comments": "1"
        },
        "user": {
            "id": "ankurnagpal",
            "image": "https://pbs.twimg.com/profile_images/378800000380805572/5a1ed3ef902a69e7fdfe46dd03c2c666_normal.jpeg",
            "twitter": "ankurnagpal",
            "name": "Ankur Nagpal",
            "tagline": "Founder, Fedora"
        }
    },
    {
        "id": 3,
        "post": {
            "votes": "104",
            "link": "/l/a0a89457ab",
            "name": "Dorm Room Tycoon",
            "tagline": "Podcast show that interviews influential innovators",
            "ph_url": "posts/dorm-room-tycoon",
            "comments": "11"
        },
        "user": {
            "id": "williamchanner",
            "image": "https://pbs.twimg.com/profile_images/3472249698/377e2a61fbf0bc296705ab75ef3cda0c_normal.png",
            "twitter": "williamchanner",
            "name": "William Channer",
            "tagline": "Founder of Dorm Room Tycoon"
        }
    },
    {
        "id": 4,
        "post": {
            "votes": "77",
            "link": "/l/29dbf7091a",
            "name": "Latergramme",
            "tagline": "Schedule and manage your Instagram posts",
            "ph_url": "posts/latergramme",
            "comments": "12"
        },
        "user": {
            "id": "symana",
            "image": "http://pbs.twimg.com/profile_images/438846853929377792/9zQGJcxh_normal.jpeg",
            "twitter": "symana",
            "name": "Matt Smith",
            "tagline": "Founder, Latergramme &amp; Thinkific "
        }
    },
    {
        "id": 5,
        "post": {
            "votes": "43",
            "link": "/l/f7108bf7e3",
            "name": "Hero4",
            "tagline": "The Most Powerful GoPro Lineup, Ever",
            "ph_url": "posts/hero4",
            "comments": "2"
        },
        "user": {
            "id": "erictwillis",
            "image": "https://pbs.twimg.com/profile_images/2272007191/wvrexvyjybx1zx9flwi7_normal.jpeg",
            "twitter": "erictwillis",
            "name": "Eric Willis",
            "tagline": "Founder, Near Inc. "
        }
    },
    {
        "id": 6,
        "post": {
            "votes": "47",
            "link": "/l/d63bd5ed26",
            "name": "Human 3",
            "tagline": "Move 30 mins or more, every day (now synced w/ iOS Health)",
            "ph_url": "posts/human-3",
            "comments": "6"
        },
        "user": {
            "id": "renn",
            "image": "https://pbs.twimg.com/profile_images/431031454877769728/95D9Z6FL_normal.png",
            "twitter": "renn",
            "name": "Renato Valdés",
            "tagline": "Co-founder, Human"
        }
    },
    {
        "id": 7,
        "post": {
            "votes": "35",
            "link": "/l/6365118d4f",
            "name": "Zova",
            "tagline": "Workouts for women",
            "ph_url": "posts/zova",
            "comments": "9"
        },
        "user": {
            "id": "nikkielizdemere",
            "image": "https://pbs.twimg.com/profile_images/462976562275430400/7n6vDLrd_normal.jpeg",
            "twitter": "nikkielizdemere",
            "name": "Nichole Elizabeth",
            "tagline": "Community at Product Hunt"
        }
    },
    {
        "id": 8,
        "post": {
            "votes": "64",
            "link": "/l/a7d6e03511",
            "name": "Inline Manual",
            "tagline": "Simplify Web Applications With Interactive Inline Tutorials",
            "ph_url": "posts/inline-manual",
            "comments": "7"
        },
        "user": {
            "id": "bogomep",
            "image": "https://pbs.twimg.com/profile_images/483546807314567170/snRp7UnU_normal.jpeg",
            "twitter": "bogomep",
            "name": "Bogomil Shopov -Bogo",
            "tagline": "Marketer, Doer, Developer, Hacker"
        }
    },
    {
        "id": 9,
        "post": {
            "votes": "16",
            "link": "/l/6abcf67894",
            "name": "Noice",
            "tagline": "Emoji Your Friends Can Hear (😃 + 🔊)",
            "ph_url": "posts/noice",
            "comments": "7"
        },
        "user": {
            "id": "bradmahler",
            "image": "https://pbs.twimg.com/profile_images/489897330573721601/Yy5tcQqh_normal.jpeg",
            "twitter": "bradmahler",
            "name": "Brad Mahler",
            "tagline": "Cofounder, Studio Tentpole"
        }
    },
    {
        "id": 10,
        "post": {
            "votes": "12",
            "link": "/l/4d6d1a7fc2",
            "name": "Up by Jawbone",
            "tagline": "Guiding you to a better, healthier you (no wristband req.)",
            "ph_url": "posts/up-by-jawbone-2",
            "comments": "1"
        },
        "user": {
            "id": "erictwillis",
            "image": "https://pbs.twimg.com/profile_images/2272007191/wvrexvyjybx1zx9flwi7_normal.jpeg",
            "twitter": "erictwillis",
            "name": "Eric Willis",
            "tagline": "Founder, Near Inc. "
        }
    },
    {
        "id": 11,
        "post": {
            "votes": "19",
            "link": "/l/d6a0aa59f4",
            "name": "RealTimeToe",
            "tagline": "Play Tic Tac Toe With Random People [iOS]",
            "ph_url": "posts/realtimetoe",
            "comments": "5"
        },
        "user": {
            "id": "Larkef",
            "image": "https://pbs.twimg.com/profile_images/431826706156879872/-2EGNjN4_normal.jpeg",
            "twitter": "Larkef",
            "name": "Jord Riekwel",
            "tagline": "Logo Designer"
        }
    },
    {
        "id": 12,
        "post": {
            "votes": "12",
            "link": "/l/b4da4c1255",
            "name": "AirSonos",
            "tagline": "Airplay to your favorite Sonos devices.",
            "ph_url": "posts/airsonos",
            "comments": "2"
        },
        "user": {
            "id": "hopkinschris",
            "image": "http://pbs.twimg.com/profile_images/2624052033/beizw6v2ycrhas0e6tgg_normal.jpeg",
            "twitter": "hopkinschris",
            "name": "Christopher Hopkins",
            "tagline": "Software Developer"
        }
    },
    {
        "id": 13,
        "post": {
            "votes": "16",
            "link": "/l/536c946823",
            "name": "Dock Name",
            "tagline": "Go on, ask for a domain. Crowdsourced domain recommendations",
            "ph_url": "posts/dock-name",
            "comments": "4"
        },
        "user": {
            "id": "mightyalex",
            "image": "http://pbs.twimg.com/profile_images/510181983876440064/wPxNUvx3_normal.jpeg",
            "twitter": "mightyalex",
            "name": "Mighty Alex",
            "tagline": "UX/UI Designer, MightyAlex.com"
        }
    },
    {
        "id": 14,
        "post": {
            "votes": "2",
            "link": "/l/acc56287d1",
            "name": "Strudel",
            "tagline": "Collect all photos in one album",
            "ph_url": "posts/strudel",
            "comments": "1"
        },
        "user": {
            "id": "Jonnotie",
            "image": "https://pbs.twimg.com/profile_images/1574116670/3782F314-B2F5-4C5A-A7C6-44DC17423313",
            "twitter": "Jonnotie",
            "name": "Jonno Riekwel",
            "tagline": "Product Designer, Founder of Polyon.co"
        }
    },
    {
        "id": 15,
        "post": {
            "votes": "9",
            "link": "/l/333a552882",
            "name": "Ring",
            "tagline": "A Home Security Solution That Also Greets Your Visitors",
            "ph_url": "posts/ring",
            "comments": "3"
        },
        "user": {
            "id": "kwdinc",
            "image": "http://pbs.twimg.com/profile_images/511717843021230080/9lPYOpSr_normal.jpeg",
            "twitter": "kwdinc",
            "name": "Kevin William David",
            "tagline": "Co-Founder,WalletKit"
        }
    },
    {
        "id": 16,
        "post": {
            "votes": "8",
            "link": "/l/ab0f2f5135",
            "name": "Sam",
            "tagline": "The internet of everything, for everyone.",
            "ph_url": "posts/sam",
            "comments": "1"
        },
        "user": {
            "id": "_jamesmundy",
            "image": "https://pbs.twimg.com/profile_images/511109606118920192/i_Bax1_A_normal.jpeg",
            "twitter": "_jamesmundy",
            "name": "James Mundy",
            "tagline": "Founder, Foundbite"
        }
    },
    {
        "id": 17,
        "post": {
            "votes": "8",
            "link": "/l/db67b57972",
            "name": "Twitter Conversation Vis",
            "tagline": "Conversations on Twitter have lives of their own.",
            "ph_url": "posts/twitter-conversation-vis",
            "comments": "2"
        },
        "user": {
            "id": "hopkinschris",
            "image": "http://pbs.twimg.com/profile_images/2624052033/beizw6v2ycrhas0e6tgg_normal.jpeg",
            "twitter": "hopkinschris",
            "name": "Christopher Hopkins",
            "tagline": "Software Developer"
        }
    },
    {
        "id": 18,
        "post": {
            "votes": "7",
            "link": "/l/db3f5779cf",
            "name": "RWND",
            "tagline": "Record and share backwards videos on your phone",
            "ph_url": "posts/rwnd",
            "comments": "0"
        },
        "user": {
            "id": "chrisvoss",
            "image": "http://pbs.twimg.com/profile_images/497285448478494720/WwLTc2WS_normal.jpeg",
            "twitter": "chrisvoss",
            "name": "CHRIS VOSS",
            "tagline": ""
        }
    },
    {
        "id": 19,
        "post": {
            "votes": "25",
            "link": "/l/949525247d",
            "name": "TinEye Reverse Img Search",
            "tagline": "Find out where an image came from &amp; how it&#39;s used.",
            "ph_url": "posts/tineye-reverse-img-search",
            "comments": "2"
        },
        "user": {
            "id": "Larkef",
            "image": "https://pbs.twimg.com/profile_images/431826706156879872/-2EGNjN4_normal.jpeg",
            "twitter": "Larkef",
            "name": "Jord Riekwel",
            "tagline": "Logo Designer"
        }
    },
    {
        "id": 20,
        "post": {
            "votes": "2",
            "link": "/l/af46ade6c3",
            "name": "Happy Sale",
            "tagline": "Nice Worldwide Second Hand Marketplace",
            "ph_url": "posts/happy-sale",
            "comments": "1"
        },
        "user": {
            "id": "UXAndrew",
            "image": "https://pbs.twimg.com/profile_images/3438689982/16091207114cb290f628f47abad96e81_normal.png",
            "twitter": "UXAndrew",
            "name": "Andrew Zusman",
            "tagline": "UX Designer"
        }
    },
    {
        "id": 21,
        "post": {
            "votes": "6",
            "link": "/l/5370c8e269",
            "name": "iSpeech",
            "tagline": "Implement speaking text feature to your app!",
            "ph_url": "posts/ispeech",
            "comments": "1"
        },
        "user": {
            "id": "kwdinc",
            "image": "http://pbs.twimg.com/profile_images/511717843021230080/9lPYOpSr_normal.jpeg",
            "twitter": "kwdinc",
            "name": "Kevin William David",
            "tagline": "Co-Founder,WalletKit"
        }
    },
    {
        "id": 22,
        "post": {
            "votes": "22",
            "link": "/l/49a43d79c7",
            "name": "2Do",
            "tagline": "Tasks management for productivity junkies",
            "ph_url": "posts/2do",
            "comments": "2"
        },
        "user": {
            "id": "RedwanKayal",
            "image": "http://pbs.twimg.com/profile_images/482442782590521344/iwPeIBQO_normal.jpeg",
            "twitter": "RedwanKayal",
            "name": "Redwan Kayal",
            "tagline": ""
        }
    },
    {
        "id": 23,
        "post": {
            "votes": "9",
            "link": "/l/4b585378c3",
            "name": "Atlas Solutions",
            "tagline": "Ad Platform With Cross-Device Targeting by Facebook",
            "ph_url": "posts/atlas-solutions",
            "comments": "1"
        },
        "user": {
            "id": "bradmenezes",
            "image": "https://pbs.twimg.com/profile_images/445441223075958784/POOt0RK7_normal.png",
            "twitter": "bradmenezes",
            "name": "Brad Menezes",
            "tagline": "Product Manager, Yelp"
        }
    },
    {
        "id": 24,
        "post": {
            "votes": "15",
            "link": "/l/c71e9c0051",
            "name": "Bistro",
            "tagline": "The smartest cat feeder. Ever.",
            "ph_url": "posts/bistro-2",
            "comments": "1"
        },
        "user": {
            "id": "bramk",
            "image": "http://pbs.twimg.com/profile_images/505754869605474305/VMPabp4p_normal.jpeg",
            "twitter": "bramk",
            "name": "Bram Kanstein",
            "tagline": "Startup Strategy &amp; Product Development"
        }
    }
]