[
    {
        "id": 1,
        "post": {
            "votes": "23",
            "link": "/l/3a45b6bcc3",
            "name": "winamp2-js",
            "tagline": "Winamp 2 in HTML5 ",
            "ph_url": "posts/winamp2-js",
            "comments": "1"
        },
        "user": {
            "id": "djug",
            "image": "http://aws.hunt-cdn.com/profile_image/65750/1414981336-a3a477e01a53eb16f561cd1f9f4ee8bf30.png",
            "twitter": "djug",
            "name": "Youghourta Benali",
            "tagline": "Founder, Passwordless"
        }
    },
    {
        "id": 2,
        "post": {
            "votes": "23",
            "link": "/l/e0b4fb4dc5",
            "name": "Winkli",
            "tagline": "Discover who you&#39;ll bump into at your Facebook events",
            "ph_url": "posts/winkli",
            "comments": "1"
        },
        "user": {
            "id": "ojaouen",
            "image": "http://aws.hunt-cdn.com/profile_image/87652/1415050455-fba00b0bcff377ca2d3a895e08fc567930.jpeg",
            "twitter": "ojaouen",
            "name": "Olivier Jaouen",
            "tagline": "Product Marketing Manager at Dexem"
        }
    },
    {
        "id": 3,
        "post": {
            "votes": "10",
            "link": "/l/da0b2f69c0",
            "name": "Paperwallet",
            "tagline": "Super thin tyvek wallets designed by artists",
            "ph_url": "posts/paperwallet",
            "comments": "0"
        },
        "user": {
            "id": "benln",
            "image": "http://aws.hunt-cdn.com/profile_image/75552/1415000642-e78d1f6c7bb2a4f53fd0bfe51fb31d7c30.png",
            "twitter": "benln",
            "name": "Ben Lang",
            "tagline": "Cofounder, Mappedly"
        }
    },
    {
        "id": 4,
        "post": {
            "votes": "4",
            "link": "/l/e86124544b",
            "name": "Bitcoin Billionaire",
            "tagline": "Clicker game about raking in bitcoins &amp; building a fortune.",
            "ph_url": "posts/bitcoin-billionaire",
            "comments": "1"
        },
        "user": {
            "id": "Larkef",
            "image": "http://aws.hunt-cdn.com/profile_image/99643/1415116826--2EGNjN430.jpeg",
            "twitter": "Larkef",
            "name": "Jord Riekwel",
            "tagline": "Logo Designer"
        }
    },
    {
        "id": 5,
        "post": {
            "votes": "3",
            "link": "/l/d9d9ad0390",
            "name": "Jail Education Solutions",
            "tagline": "Tablet-based Education for Prisoners",
            "ph_url": "posts/jail-education-solutions",
            "comments": "2"
        },
        "user": {
            "id": "UXAndrew",
            "image": "http://aws.hunt-cdn.com/profile_image/86908/1415048379-16091207114cb290f628f47abad96e8130.png",
            "twitter": "UXAndrew",
            "name": "Andrew Zusman",
            "tagline": "UX Designer"
        }
    },
    {
        "id": 6,
        "post": {
            "votes": "3",
            "link": "/l/6db57356ec",
            "name": "Boosted Single and Dual",
            "tagline": "The most advanced and powerful electric skateboards",
            "ph_url": "posts/boosted-single-and-dual",
            "comments": "0"
        },
        "user": {
            "id": "_DanFriedman",
            "image": "http://aws.hunt-cdn.com/profile_image/48651/1414955083-hMiuOza930.png",
            "twitter": "_DanFriedman",
            "name": "Dan Friedman",
            "tagline": "http://dfriedman.co"
        }
    },
    {
        "id": 7,
        "post": {
            "votes": "4",
            "link": "/l/8fd4a9fda7",
            "name": "proxygen",
            "tagline": "Facebook&#39;s C++ HTTP Libraries",
            "ph_url": "posts/proxygen",
            "comments": "0"
        },
        "user": {
            "id": "djug",
            "image": "http://aws.hunt-cdn.com/profile_image/65750/1414981336-a3a477e01a53eb16f561cd1f9f4ee8bf30.png",
            "twitter": "djug",
            "name": "Youghourta Benali",
            "tagline": "Founder, Passwordless"
        }
    },
    {
        "id": 8,
        "post": {
            "votes": "1",
            "link": "/l/1ce405c498",
            "name": "Solartab",
            "tagline": "The premium solar charger for smartphones and tablets.",
            "ph_url": "posts/solartab",
            "comments": "0"
        },
        "user": {
            "id": "nzieber",
            "image": "http://aws.hunt-cdn.com/profile_image/81278/1415025718-hd6dVi5l30.jpeg",
            "twitter": "nzieber",
            "name": "Nick Zieber",
            "tagline": "Consultant - JAC Recruitment (Hong Kong)"
        }
    },
    {
        "id": 9,
        "post": {
            "votes": "4",
            "link": "/l/f3a46e49c4",
            "name": "Number March",
            "tagline": "Tower Defense Game with Marching Numbers",
            "ph_url": "posts/number-march",
            "comments": "1"
        },
        "user": {
            "id": "gozdeaksay",
            "image": "http://aws.hunt-cdn.com/profile_image/48967/1414955430-E_3gnwKT30.jpeg",
            "twitter": "gozdeaksay",
            "name": "Gozde Aksay",
            "tagline": "Co-Founder, Salary Fairy"
        }
    },
    {
        "id": 10,
        "post": {
            "votes": "2",
            "link": "/l/41f489a88f",
            "name": "Gondola",
            "tagline": "The web framework for Go programming language",
            "ph_url": "posts/gondola",
            "comments": "0"
        },
        "user": {
            "id": "djug",
            "image": "http://aws.hunt-cdn.com/profile_image/65750/1414981336-a3a477e01a53eb16f561cd1f9f4ee8bf30.png",
            "twitter": "djug",
            "name": "Youghourta Benali",
            "tagline": "Founder, Passwordless"
        }
    },
    {
        "id": 11,
        "post": {
            "votes": "1",
            "link": "/l/f8fcaf5986",
            "name": "eNcade (Kickstarter)",
            "tagline": "A Portable Raspberry Pi Gaming Console",
            "ph_url": "posts/encade-kickstarter",
            "comments": "1"
        },
        "user": {
            "id": "riaface",
            "image": "http://aws.hunt-cdn.com/profile_image/99444/1415116525-fXzJdjIs30.jpeg",
            "twitter": "riaface",
            "name": "Ria Blagburn",
            "tagline": "Co-founder, emble"
        }
    }
]