[
    {
        "id": 1,
        "post": {
            "votes": "576",
            "link": "/l/5b6c78063b",
            "name": "Forest",
            "tagline": "Stay focused, stop phubbing"
        }
    },
    {
        "id": 2,
        "post": {
            "votes": "151",
            "link": "/l/9648068b18",
            "name": "RunSwift",
            "tagline": "Try Swift in Your Browser"
        }
    },
    {
        "id": 3,
        "post": {
            "votes": "122",
            "link": "/l/605dfb591b",
            "name": "Instacode",
            "tagline": "Instagram for code snippets"
        }
    },
    {
        "id": 4,
        "post": {
            "votes": "96",
            "link": "/l/6a90b367b1",
            "name": "Armature",
            "tagline": "The ultimate wireframing extension for Adobe Illustrator"
        }
    },
    {
        "id": 5,
        "post": {
            "votes": "98",
            "link": "/l/667b5cf210",
            "name": "Encore Beat",
            "tagline": "Product Hunt for electronic music"
        }
    },
    {
        "id": 6,
        "post": {
            "votes": "77",
            "link": "/l/7bfb0285ed",
            "name": "Target Process",
            "tagline": "Visually plan and track Scrum, Kanban, and more"
        }
    },
    {
        "id": 7,
        "post": {
            "votes": "64",
            "link": "/l/36d49309ba",
            "name": "Shiny",
            "tagline": "A web application framework for R"
        }
    },
    {
        "id": 8,
        "post": {
            "votes": "56",
            "link": "/l/57d0d8bcf7",
            "name": "Kindr",
            "tagline": "The app that makes it fun and easy to brighten someone&#39;s day"
        }
    },
    {
        "id": 9,
        "post": {
            "votes": "50",
            "link": "/l/e1d73716ad",
            "name": "Golala",
            "tagline": "Crazy Eights for iPhone"
        }
    },
    {
        "id": 10,
        "post": {
            "votes": "49",
            "link": "/l/e21af46628",
            "name": "Mail-in-a-Box",
            "tagline": "easy-to-deploy mail server in a box."
        }
    },
    {
        "id": 11,
        "post": {
            "votes": "44",
            "link": "/l/4cae6b7ca2",
            "name": "Tailor",
            "tagline": "Your New Virtual Graphic Designer"
        }
    },
    {
        "id": 12,
        "post": {
            "votes": "35",
            "link": "/l/92d1f2fe1e",
            "name": "Skim.It",
            "tagline": "Save, sort and share the good stuff you find online."
        }
    },
    {
        "id": 13,
        "post": {
            "votes": "25",
            "link": "/l/4699a5b2e9",
            "name": "Retrospecs",
            "tagline": "Create photos of the present from the past"
        }
    },
    {
        "id": 14,
        "post": {
            "votes": "24",
            "link": "/l/fb3d666390",
            "name": "Bux",
            "tagline": "Casual stock trading - thumb swipes only"
        }
    },
    {
        "id": 15,
        "post": {
            "votes": "17",
            "link": "/l/ecbaca6b3e",
            "name": "Sports Injury Predictor",
            "tagline": "Predicts Injuries for NFL Players"
        }
    },
    {
        "id": 16,
        "post": {
            "votes": "9",
            "link": "/l/e15796bfb5",
            "name": "GhostTunes",
            "tagline": "iTunes alternative by Garth Brooks"
        }
    },
    {
        "id": 17,
        "post": {
            "votes": "15",
            "link": "/l/73b55c2ced",
            "name": "Osios",
            "tagline": "Effortless collaboration for app developers and clients"
        }
    }
]