[
  {
    "id": 12587,
    "post": {
      "votes": 862,
      "link": "http://well.blogs.nytimes.com/projects/workouts/?ref=phnest.in",
      "name": "7 Minute Workout",
      "tagline": "Scientific 7 Minute Workout app from the New York Times",
      "ph_url": "http://well.blogs.nytimes.com/projects/workouts/?ref=phnest.in",
      "comments": 21
    },
    "user": {
      "id": "robjama",
      "image": "https://ph-avatars.imgix.net/642/original?auto=format&fit=crop&crop=faces&w=160&h=160",
      "twitter": "robjama",
      "name": "Robleh Jama",
      "tagline": "Founder, Tiny Hearts / Next Keyboard"
    }
  },
  {
    "id": 12589,
    "post": {
      "votes": 573,
      "link": "http://hocusfoc.us?ref=phnest.in",
      "name": "Hocus Focus",
      "tagline": "A Mac menu bar utility that hides your inactive windows",
      "ph_url": "http://hocusfoc.us?ref=phnest.in",
      "comments": 26
    },
    "user": {
      "id": "measuredweighed",
      "image": "https://ph-avatars.imgix.net/58042/original?auto=format&fit=crop&crop=faces&w=160&h=160",
      "twitter": "measuredweighed",
      "name": "Nial",
      "tagline": "Developer"
    }
  },
  {
    "id": 12583,
    "post": {
      "votes": 355,
      "link": "http://monitority.com/vip?subid=ph&ref=phnest.in",
      "name": "Monitority",
      "tagline": "Simple website monitoring service (sms/email alerts)",
      "ph_url": "http://monitority.com/vip?subid=ph&ref=phnest.in",
      "comments": 15
    },
    "user": {
      "id": "benln",
      "image": "https://ph-avatars.imgix.net/1880/original?auto=format&fit=crop&crop=faces&w=160&h=160",
      "twitter": "benln",
      "name": "Ben Lang",
      "tagline": "Cofounder, Mapme"
    }
  },
  {
    "id": 12594,
    "post": {
      "votes": 311,
      "link": "http://www.howigotmyfirst3customers.com/?ref=phnest.in",
      "name": "First 3 Customers",
      "tagline": "Stories of how entrepreneurs got their first three customers",
      "ph_url": "http://www.howigotmyfirst3customers.com/?ref=phnest.in",
      "comments": 5
    },
    "user": {
      "id": "_jacksmith",
      "image": "https://ph-avatars.imgix.net/962/original?auto=format&fit=crop&crop=faces&w=160&h=160",
      "twitter": "_jacksmith",
      "name": "Jack Smith",
      "tagline": "Serial Entrepreneur & Startup Adviser"
    }
  },
  {
    "id": 12612,
    "post": {
      "votes": 212,
      "link": "http://designers.watch/?ref=phnest.in",
      "name": "Designers Watch",
      "tagline": "The must-see documentaries for designers and artists",
      "ph_url": "http://designers.watch/?ref=phnest.in",
      "comments": 3
    },
    "user": {
      "id": "kwdinc",
      "image": "https://ph-avatars.imgix.net/79/original?auto=format&fit=crop&crop=faces&w=160&h=160",
      "twitter": "kwdinc",
      "name": "Kevin William David",
      "tagline": "Co-Founder, Sonder"
    }
  },
  {
    "id": 12606,
    "post": {
      "votes": 201,
      "link": "http://babyname-app.com/?ref=phnest.in",
      "name": "Babyname",
      "tagline": "Tinder for baby names (no, really)",
      "ph_url": "http://babyname-app.com/?ref=phnest.in",
      "comments": 39
    },
    "user": {
      "id": "edtoh",
      "image": "https://ph-avatars.imgix.net/4439/original?auto=format&fit=crop&crop=faces&w=160&h=160",
      "twitter": "edtoh",
      "name": "Edwin Toh",
      "tagline": "Founder, Garage Interactive"
    }
  },
  {
    "id": 12585,
    "post": {
      "votes": 155,
      "link": "https://github.com/fitztrev/make-it-rain?ref=phnest.in",
      "name": "Make It Rain",
      "tagline": "Random gifs when you get paid via Stripe (Slack and Hipchat)",
      "ph_url": "https://github.com/fitztrev/make-it-rain?ref=phnest.in",
      "comments": 9
    },
    "user": {
      "id": "riaface",
      "image": "https://ph-avatars.imgix.net/1565/original?auto=format&fit=crop&crop=faces&w=160&h=160",
      "twitter": "riaface",
      "name": "Ria Blagburn",
      "tagline": "Founder, GrowBeyond"
    }
  },
  {
    "id": 12605,
    "post": {
      "votes": 174,
      "link": "https://flowvella.com/?ref=phnest.in",
      "name": "FlowVella",
      "tagline": "Easiest Way to Beautiful Presentations",
      "ph_url": "https://flowvella.com/?ref=phnest.in",
      "comments": 16
    },
    "user": {
      "id": "hnshah",
      "image": "https://ph-avatars.imgix.net/23/original?auto=format&fit=crop&crop=faces&w=160&h=160",
      "twitter": "hnshah",
      "name": "Hiten Shah",
      "tagline": "Crazy Egg, KISSmetrics & Quick Sprout"
    }
  },
  {
    "id": 12590,
    "post": {
      "votes": 123,
      "link": "https://www.twelvesouth.com/product/hoverbar-for-ipad?ref=phnest.in",
      "name": "Hoverbar for iPad",
      "tagline": "Flexible arm that attaches anywhere you use your iPad",
      "ph_url": "https://www.twelvesouth.com/product/hoverbar-for-ipad?ref=phnest.in",
      "comments": 4
    },
    "user": {
      "id": "dshan",
      "image": "https://ph-avatars.imgix.net/13/original?auto=format&fit=crop&crop=faces&w=160&h=160",
      "twitter": "dshan",
      "name": "Derek Shanahan",
      "tagline": "Accounts & Biz Dev at Playerize"
    }
  },
  {
    "id": 12603,
    "post": {
      "votes": 123,
      "link": "http://give-n-go.co?ref=phnest.in",
      "name": "Give ’n’ Go",
      "tagline": "A curated gallery of Dribbble shots as interactive code pens",
      "ph_url": "http://give-n-go.co?ref=phnest.in",
      "comments": 3
    },
    "user": {
      "id": "brian_lovin",
      "image": "https://ph-avatars.imgix.net/6358/original?auto=format&fit=crop&crop=faces&w=160&h=160",
      "twitter": "brian_lovin",
      "name": "Brian Lovin",
      "tagline": "Product Designer, Facebook"
    }
  },
  {
    "id": 12602,
    "post": {
      "votes": 90,
      "link": "http://relax.li/?ref=phnest.in",
      "name": "Relax.li",
      "tagline": "Pure relaxation in your browser",
      "ph_url": "http://relax.li/?ref=phnest.in",
      "comments": 13
    },
    "user": {
      "id": "robjama",
      "image": "https://ph-avatars.imgix.net/642/original?auto=format&fit=crop&crop=faces&w=160&h=160",
      "twitter": "robjama",
      "name": "Robleh Jama",
      "tagline": "Founder, Tiny Hearts / Next Keyboard"
    }
  },
  {
    "id": 12595,
    "post": {
      "votes": 78,
      "link": "http://misterspoils.com/?ref=phnest.in",
      "name": "Mister Spoils",
      "tagline": "A Simple Email Filled With Beautiful Things",
      "ph_url": "http://misterspoils.com/?ref=phnest.in",
      "comments": 3
    },
    "user": {
      "id": "dshan",
      "image": "https://ph-avatars.imgix.net/13/original?auto=format&fit=crop&crop=faces&w=160&h=160",
      "twitter": "dshan",
      "name": "Derek Shanahan",
      "tagline": "Accounts & Biz Dev at Playerize"
    }
  },
  {
    "id": 12597,
    "post": {
      "votes": 66,
      "link": "http://tiesociety.com?ref=phnest.in",
      "name": "Tie Society",
      "tagline": "Netflix for ties",
      "ph_url": "http://tiesociety.com?ref=phnest.in",
      "comments": 12
    },
    "user": {
      "id": "eriktorenberg",
      "image": "https://ph-avatars.imgix.net/8319/original?auto=format&fit=crop&crop=faces&w=160&h=160",
      "twitter": "eriktorenberg",
      "name": "Erik Torenberg",
      "tagline": "Product Hunt"
    }
  },
  {
    "id": 12582,
    "post": {
      "votes": 68,
      "link": "http://www.stethee.com/?ref=phnest.in#/stethee",
      "name": "Stethee",
      "tagline": "Stethoscope for the 21st century (Kickstarter)",
      "ph_url": "http://www.stethee.com/?ref=phnest.in#/stethee",
      "comments": 4
    },
    "user": {
      "id": "pieterpaul",
      "image": "https://ph-avatars.imgix.net/14307/original?auto=format&fit=crop&crop=faces&w=160&h=160",
      "twitter": "pieterpaul",
      "name": "Pieter Walraven",
      "tagline": "Founder & Product @ Pie - pie.co"
    }
  },
  {
    "id": 12614,
    "post": {
      "votes": 68,
      "link": "http://pullquote.com/?ref=phnest.in",
      "name": "Pullquote",
      "tagline": "Tweet quotes and cropped images from the web easily",
      "ph_url": "http://pullquote.com/?ref=phnest.in",
      "comments": 1
    },
    "user": {
      "id": "chrismessina",
      "image": "https://ph-avatars.imgix.net/18280/original?auto=format&fit=crop&crop=faces&w=160&h=160",
      "twitter": "chrismessina",
      "name": "Chris Messina ✁_____",
      "tagline": "Developer Experience Lead at @Uber"
    }
  },
  {
    "id": 12607,
    "post": {
      "votes": 55,
      "link": "http://tapchat.com/?ref=phnest.in",
      "name": "TapChat",
      "tagline": "WhatsApp for Strangers",
      "ph_url": "http://tapchat.com/?ref=phnest.in",
      "comments": 7
    },
    "user": {
      "id": "joelandren",
      "image": "https://ph-avatars.imgix.net/270/original?auto=format&fit=crop&crop=faces&w=160&h=160",
      "twitter": "joelandren",
      "name": "Joel Andren",
      "tagline": "co-founder, PressFriendly"
    }
  },
  {
    "id": 12593,
    "post": {
      "votes": 49,
      "link": "https://www.kickstarter.com/projects/cobi/cobi-worlds-smartest-connected-biking-system?ref=phnest.in",
      "name": "COBI",
      "tagline": "Connected biking (pre-launch)",
      "ph_url": "https://www.kickstarter.com/projects/cobi/cobi-worlds-smartest-connected-biking-system?ref=phnest.in",
      "comments": 3
    },
    "user": {
      "id": "kristofertm",
      "image": "https://ph-avatars.imgix.net/851/original?auto=format&fit=crop&crop=faces&w=160&h=160",
      "twitter": "kristofertm",
      "name": "Kristofer™",
      "tagline": "Founder @ Lamplighter Labs"
    }
  },
  {
    "id": 12581,
    "post": {
      "votes": 45,
      "link": "http://wheretowatch.com/?ref=phnest.in",
      "name": "Where to Watch",
      "tagline": "MPAA-approved sources of movies and TV shows",
      "ph_url": "http://wheretowatch.com/?ref=phnest.in",
      "comments": 7
    },
    "user": {
      "id": "chrismessina",
      "image": "https://ph-avatars.imgix.net/18280/original?auto=format&fit=crop&crop=faces&w=160&h=160",
      "twitter": "chrismessina",
      "name": "Chris Messina ✁_____",
      "tagline": "Developer Experience Lead at @Uber"
    }
  },
  {
    "id": 12601,
    "post": {
      "votes": 43,
      "link": "http://www.soundwavemug.com/?ref=phnest.in",
      "name": "SoundwaveMug",
      "tagline": "Create a mug of your favorite (Soundcloud) song's soundwave",
      "ph_url": "http://www.soundwavemug.com/?ref=phnest.in",
      "comments": 6
    },
    "user": {
      "id": "rrhoover",
      "image": "https://ph-avatars.imgix.net/2/original?auto=format&fit=crop&crop=faces&w=160&h=160",
      "twitter": "rrhoover",
      "name": "Ryan Hoover",
      "tagline": "Product Hunt"
    }
  },
  {
    "id": 12596,
    "post": {
      "votes": 55,
      "link": "http://round.me/?ref=phnest.in",
      "name": "Roundme",
      "tagline": "Virtual tour made simple",
      "ph_url": "http://round.me/?ref=phnest.in",
      "comments": 1
    },
    "user": {
      "id": "rubenvivanti",
      "image": "https://ph-avatars.imgix.net/127817/original?auto=format&fit=crop&crop=faces&w=160&h=160",
      "twitter": "rubenvivanti",
      "name": "Ruben",
      "tagline": ""
    }
  },
  {
    "id": 12600,
    "post": {
      "votes": 40,
      "link": "http://indushunter.com?ref=phnest.in",
      "name": "Indus Hunter",
      "tagline": "Product Hunt for Indian products and startups",
      "ph_url": "http://indushunter.com?ref=phnest.in",
      "comments": 2
    },
    "user": {
      "id": "neerajt4",
      "image": "https://ph-avatars.imgix.net/687/original?auto=format&fit=crop&crop=faces&w=160&h=160",
      "twitter": "neerajt4",
      "name": "Neeraj Thakur",
      "tagline": "Marketer | www.neerajt.com"
    }
  },
  {
    "id": 12591,
    "post": {
      "votes": 39,
      "link": "https://pacthealth.com/?ref=phnest.in",
      "name": "PactHealth",
      "tagline": "Lower your deductible with every workout",
      "ph_url": "https://pacthealth.com/?ref=phnest.in",
      "comments": 0
    },
    "user": {
      "id": "_jacksmith",
      "image": "https://ph-avatars.imgix.net/962/original?auto=format&fit=crop&crop=faces&w=160&h=160",
      "twitter": "_jacksmith",
      "name": "Jack Smith",
      "tagline": "Serial Entrepreneur & Startup Adviser"
    }
  },
  {
    "id": 12611,
    "post": {
      "votes": 41,
      "link": "http://www.dangerdragon.com/?ref=phnest.in",
      "name": "Danger Dragon",
      "tagline": "A simple game to test your focus",
      "ph_url": "http://www.dangerdragon.com/?ref=phnest.in",
      "comments": 2
    },
    "user": {
      "id": "nbashaw",
      "image": "https://ph-avatars.imgix.net/1/original?auto=format&fit=crop&crop=faces&w=160&h=160",
      "twitter": "nbashaw",
      "name": "Nathan Bashaw",
      "tagline": "Building a new kind of electronic book"
    }
  },
  {
    "id": 12588,
    "post": {
      "votes": 34,
      "link": "https://solon.rocks/?ref=phnest.in",
      "name": "Solon",
      "tagline": "Collaborative jukebox using YouTube, Vimeo and SoundCloud ",
      "ph_url": "https://solon.rocks/?ref=phnest.in",
      "comments": 4
    },
    "user": {
      "id": "erictwillis",
      "image": "https://ph-avatars.imgix.net/16056/original?auto=format&fit=crop&crop=faces&w=160&h=160",
      "twitter": "erictwillis",
      "name": "Eric Willis",
      "tagline": "Mod @Product Hunt/ Founder @Chatmunk"
    }
  },
  {
    "id": 12608,
    "post": {
      "votes": 31,
      "link": "https://www.singular.net/?ref=phnest.in",
      "name": "Singular",
      "tagline": "Simplified Mobile Marketing: One intelligent dashboard.",
      "ph_url": "https://www.singular.net/?ref=phnest.in",
      "comments": 0
    },
    "user": {
      "id": "bonatsos",
      "image": "https://ph-avatars.imgix.net/10737/original?auto=format&fit=crop&crop=faces&w=160&h=160",
      "twitter": "bonatsos",
      "name": "Niko Bonatsos",
      "tagline": "Venture Partner @ General Catalyst"
    }
  },
  {
    "id": 12598,
    "post": {
      "votes": 27,
      "link": "http://vixxenn.com/?ref=phnest.in",
      "name": "Vixxenn",
      "tagline": "Highest quality hair extensions",
      "ph_url": "http://vixxenn.com/?ref=phnest.in",
      "comments": 7
    },
    "user": {
      "id": "eriktorenberg",
      "image": "https://ph-avatars.imgix.net/8319/original?auto=format&fit=crop&crop=faces&w=160&h=160",
      "twitter": "eriktorenberg",
      "name": "Erik Torenberg",
      "tagline": "Product Hunt"
    }
  },
  {
    "id": 12586,
    "post": {
      "votes": 26,
      "link": "http://albertxing.github.io/rudolph-runner/?ref=phnest.in",
      "name": "Rudolph Runner",
      "tagline": "A one-button game. Make Rudolph clear the obstacles!",
      "ph_url": "http://albertxing.github.io/rudolph-runner/?ref=phnest.in",
      "comments": 2
    },
    "user": {
      "id": "riaface",
      "image": "https://ph-avatars.imgix.net/1565/original?auto=format&fit=crop&crop=faces&w=160&h=160",
      "twitter": "riaface",
      "name": "Ria Blagburn",
      "tagline": "Founder, GrowBeyond"
    }
  },
  {
    "id": 12610,
    "post": {
      "votes": 27,
      "link": "https://www.google.com/maps/d/u/0/edit?mid=zP60ZK9XmRZw.kKeFOZ_5nxJU&ref=phnest.in",
      "name": "Where have you cried?",
      "tagline": "Opened-sourced map of where people have publicly cried in SF",
      "ph_url": "https://www.google.com/maps/d/u/0/edit?mid=zP60ZK9XmRZw.kKeFOZ_5nxJU&ref=phnest.in",
      "comments": 5
    },
    "user": {
      "id": "lenndizzle",
      "image": "https://ph-avatars.imgix.net/193/original?auto=format&fit=crop&crop=faces&w=160&h=160",
      "twitter": "lenndizzle",
      "name": "Lenny Hu",
      "tagline": "Designer, Knowtify.io"
    }
  },
  {
    "id": 12613,
    "post": {
      "votes": 27,
      "link": "http://zing.co/?ref=phnest.in",
      "name": "Zing Point of Sale",
      "tagline": "A beautiful and powerful point-of-sale system for iPad.",
      "ph_url": "http://zing.co/?ref=phnest.in",
      "comments": 2
    },
    "user": {
      "id": "mantwan",
      "image": "https://ph-avatars.imgix.net/4443/original?auto=format&fit=crop&crop=faces&w=160&h=160",
      "twitter": "mantwan",
      "name": "Anthony Armendáriz",
      "tagline": "Partner& Design Director at Funsize"
    }
  },
  {
    "id": 12599,
    "post": {
      "votes": 32,
      "link": "http://www.merrychristmas.to/?ref=phnest.in",
      "name": "The Merry Maker",
      "tagline": "Make your own Christmas card",
      "ph_url": "http://www.merrychristmas.to/?ref=phnest.in",
      "comments": 6
    },
    "user": {
      "id": "mutlu82",
      "image": "https://ph-avatars.imgix.net/591/original?auto=format&fit=crop&crop=faces&w=160&h=160",
      "twitter": "mutlu82",
      "name": "Murat Mutlu",
      "tagline": "Co-Founder, Marvelapp"
    }
  },
  {
    "id": 12592,
    "post": {
      "votes": 22,
      "link": "https://www.recardo.me?ref=phnest.in",
      "name": "Recardo",
      "tagline": "An exclusive marketplace for fashion gift cards",
      "ph_url": "https://www.recardo.me?ref=phnest.in",
      "comments": 4
    },
    "user": {
      "id": "shiraabel",
      "image": "https://ph-avatars.imgix.net/8491/original?auto=format&fit=crop&crop=faces&w=160&h=160",
      "twitter": "shiraabel",
      "name": "Shira Abel",
      "tagline": "CEO, Hunter & Bard"
    }
  },
  {
    "id": 12604,
    "post": {
      "votes": 14,
      "link": "http://www.101touch.com/?ref=phnest.in",
      "name": "101touch",
      "tagline": "The new generation of keyboard (pre-launch)",
      "ph_url": "http://www.101touch.com/?ref=phnest.in",
      "comments": 4
    },
    "user": {
      "id": "erictwillis",
      "image": "https://ph-avatars.imgix.net/16056/original?auto=format&fit=crop&crop=faces&w=160&h=160",
      "twitter": "erictwillis",
      "name": "Eric Willis",
      "tagline": "Mod @Product Hunt/ Founder @Chatmunk"
    }
  }
]