[
    {
        "id": 1,
        "post": {
            "votes": 817,
            "link": "/r/4c743609ff/15138",
            "name": "I need a Resume",
            "tagline": "Create beautiful free resumes in seconds.",
            "ph_url": "/posts/i-need-a-resume",
            "comments": 18
        },
        "user": {
            "id": "http://www.producthunt.com/kwdinc",
            "name": "Kevin William David"
        }
    },
    {
        "id": 2,
        "post": {
            "votes": 710,
            "link": "/r/87229a02f5/15163",
            "name": "MacBook 12\"",
            "tagline": "The new 12\" MacBook with a retina display",
            "ph_url": "/posts/macbook-12",
            "comments": 39
        },
        "user": {
            "id": "http://www.producthunt.com/dankaplan",
            "name": "Dan Kaplan"
        }
    },
    {
        "id": 3,
        "post": {
            "votes": 515,
            "link": "/r/ac74304e0a/15140",
            "name": "Enhancv",
            "tagline": "Create compelling eye-catching resumes",
            "ph_url": "/posts/enhancv",
            "comments": 14
        },
        "user": {
            "id": "http://www.producthunt.com/v4violetta",
            "name": "Violeta Nedkova"
        }
    },
    {
        "id": 4,
        "post": {
            "votes": 350,
            "link": "/r/4ab655ed80/15144",
            "name": "BLACK",
            "tagline": "The stunning black + white photo app, now on iOS",
            "ph_url": "/posts/black-2",
            "comments": 25
        },
        "user": {
            "id": "http://www.producthunt.com/daniellenewnham",
            "name": "Danielle Newnham"
        }
    },
    {
        "id": 5,
        "post": {
            "votes": 352,
            "link": "/r/4eb68311d0/15153",
            "name": "Curated",
            "tagline": "Grow your audience by sharing truly engaging content weekly",
            "ph_url": "/posts/curated-2",
            "comments": 37
        },
        "user": {
            "id": "http://www.producthunt.com/hnshah",
            "name": "Hiten Shah"
        }
    },
    {
        "id": 6,
        "post": {
            "votes": 260,
            "link": "/r/475ac90910/15164",
            "name": "Apple ResearchKit",
            "tagline": "iOS medical research framework",
            "ph_url": "/posts/apple-researchkit",
            "comments": 6
        },
        "user": {
            "id": "http://www.producthunt.com/anjneymidha",
            "name": "Anjney Midha"
        }
    },
    {
        "id": 7,
        "post": {
            "votes": 206,
            "link": "/r/d5da1dfc8a/15143",
            "name": "Shitty Listings",
            "tagline": "A list of distressed properties for house flippers.",
            "ph_url": "/posts/shitty-listings",
            "comments": 8
        },
        "user": {
            "id": "http://www.producthunt.com/ilikevests",
            "name": "Kevin Hale"
        }
    },
    {
        "id": 8,
        "post": {
            "votes": 202,
            "link": "/r/6ee4be32f5/15105",
            "name": "Preload",
            "tagline": "Watch the best new videos from the web without internet",
            "ph_url": "/posts/preload",
            "comments": 17
        },
        "user": {
            "id": "http://www.producthunt.com/jonasbrandau",
            "name": "jonas brandau"
        }
    },
    {
        "id": 9,
        "post": {
            "votes": 159,
            "link": "/r/110805ddb1/15150",
            "name": "JobsInTech",
            "tagline": "Find tech jobs that come with a visa",
            "ph_url": "/posts/jobsintech",
            "comments": 4
        },
        "user": {
            "id": "http://www.producthunt.com/rahulvarshneya",
            "name": "Rahul Varshneya"
        }
    },
    {
        "id": 10,
        "post": {
            "votes": 160,
            "link": "/r/6b0870ecf4/15151",
            "name": "Marvel Android Export",
            "tagline": "Turn prototypes into Android Apps in one click",
            "ph_url": "/posts/marvel-android-export",
            "comments": 1
        },
        "user": {
            "id": "http://www.producthunt.com/mutlu82",
            "name": "Murat Mutlu"
        }
    },
    {
        "id": 11,
        "post": {
            "votes": 135,
            "link": "/r/483671016c/15137",
            "name": "Pomello",
            "tagline": "Map your company culture and improve hiring hit rates",
            "ph_url": "/posts/pomello",
            "comments": 3
        },
        "user": {
            "id": "http://www.producthunt.com/andrewjbryk",
            "name": "Andrew Bryk"
        }
    },
    {
        "id": 12,
        "post": {
            "votes": 120,
            "link": "/r/bcc783d054/15155",
            "name": "Cleartones",
            "tagline": "Minimalist ringtones",
            "ph_url": "/posts/cleartones",
            "comments": 3
        },
        "user": {
            "id": "http://www.producthunt.com/kristofertm",
            "name": "Kris Minkstein"
        }
    },
    {
        "id": 13,
        "post": {
            "votes": 148,
            "link": "/r/3f516dad7b/15146",
            "name": "App Watch List",
            "tagline": "A list of Apple Watch apps",
            "ph_url": "/posts/app-watch-list",
            "comments": 8
        },
        "user": {
            "id": "http://www.producthunt.com/erictwillis",
            "name": "Eric Willis"
        }
    },
    {
        "id": 14,
        "post": {
            "votes": 82,
            "link": "/r/0884a964c1/15161",
            "name": "Apple Watch Icon Template",
            "tagline": "Download free and pay what you want",
            "ph_url": "/posts/apple-watch-icon-template",
            "comments": 3
        },
        "user": {
            "id": "http://www.producthunt.com/kristofertm",
            "name": "Kris Minkstein"
        }
    },
    {
        "id": 15,
        "post": {
            "votes": 69,
            "link": "/r/1d0a4fb4be/15139",
            "name": "CloudMedx",
            "tagline": "AI for early disease detection and healthier outcomes",
            "ph_url": "/posts/cloudmedx",
            "comments": 1
        },
        "user": {
            "id": "http://www.producthunt.com/katmanalac",
            "name": "Kat Manalac"
        }
    },
    {
        "id": 16,
        "post": {
            "votes": 67,
            "link": "/r/d2347593f8/15154",
            "name": "Project Pulse",
            "tagline": "Project status pages communicate progress for you",
            "ph_url": "/posts/project-pulse",
            "comments": 9
        },
        "user": {
            "id": "http://www.producthunt.com/adamslieb",
            "name": "Adam Lieb"
        }
    },
    {
        "id": 17,
        "post": {
            "votes": 63,
            "link": "/r/8cd3231c3b/15158",
            "name": "Facemoji",
            "tagline": "Emoji your face (via your webcam)",
            "ph_url": "/posts/facemoji",
            "comments": 4
        },
        "user": {
            "id": "http://www.producthunt.com/cap",
            "name": "Cap Watkins"
        }
    },
    {
        "id": 18,
        "post": {
            "votes": 59,
            "link": "/r/98080527be/15157",
            "name": "Merecedes Benz F015",
            "tagline": "Autonomous vehicle research car",
            "ph_url": "/posts/merecedes-benz-f015",
            "comments": 0
        },
        "user": {
            "id": "http://www.producthunt.com/tonysheng",
            "name": "Tony Sheng"
        }
    },
    {
        "id": 19,
        "post": {
            "votes": 59,
            "link": "/r/d5ddb339bf/15145",
            "name": "Unindexed ",
            "tagline": "Websites that self-destruct after Google indexes 'em",
            "ph_url": "/posts/unindexed",
            "comments": 3
        },
        "user": {
            "id": "http://www.producthunt.com/robjama",
            "name": "Robleh Jama"
        }
    },
    {
        "id": 20,
        "post": {
            "votes": 81,
            "link": "/r/1c91fe332f/15136",
            "name": "Hibou",
            "tagline": "Use spaced repetition to help you remember what you read",
            "ph_url": "/posts/hibou",
            "comments": 1
        },
        "user": {
            "id": "http://www.producthunt.com/andrewjbryk",
            "name": "Andrew Bryk"
        }
    },
    {
        "id": 21,
        "post": {
            "votes": 60,
            "link": "/r/3c6f14a52d/15159",
            "name": "VinylHub",
            "tagline": "Every physical record shop on the planet.",
            "ph_url": "/posts/vinylhub",
            "comments": 0
        },
        "user": {
            "id": "http://www.producthunt.com/rklau",
            "name": "Rick Klau"
        }
    },
    {
        "id": 22,
        "post": {
            "votes": 50,
            "link": "/r/6faacf08d0/15167",
            "name": "It's Private",
            "tagline": "Make your tweets disappear by using hashtags",
            "ph_url": "/posts/it-s-private",
            "comments": 3
        },
        "user": {
            "id": "http://www.producthunt.com/erictwillis",
            "name": "Eric Willis"
        }
    },
    {
        "id": 23,
        "post": {
            "votes": 51,
            "link": "/r/df2687c5ae/15165",
            "name": "Papyros",
            "tagline": "Linux-based OS that adheres to Google's Material Design",
            "ph_url": "/posts/papyros",
            "comments": 2
        },
        "user": {
            "id": "http://www.producthunt.com/chrismessina",
            "name": "Chris Messina ☠"
        }
    },
    {
        "id": 24,
        "post": {
            "votes": 39,
            "link": "/r/cfb4628b7c/15156",
            "name": "Making Users Awesome",
            "tagline": "Insight into what makes certain offerings shine (book)",
            "ph_url": "/posts/making-users-awesome",
            "comments": 3
        },
        "user": {
            "id": "http://www.producthunt.com/nikkielizdemere",
            "name": "Nichole Elizabeth"
        }
    },
    {
        "id": 25,
        "post": {
            "votes": 40,
            "link": "/r/aee4040a07/15148",
            "name": "Text Palette",
            "tagline": "Type once / use anywhere. Save & reuse bits of text.",
            "ph_url": "/posts/text-palette",
            "comments": 0
        },
        "user": {
            "id": "http://www.producthunt.com/larkef",
            "name": "Jord Riekwel"
        }
    },
    {
        "id": 26,
        "post": {
            "votes": 30,
            "link": "/r/03bbaad3b0/15149",
            "name": "iCantHear",
            "tagline": "Communicate easily with the hearing impaired",
            "ph_url": "/posts/icanthear",
            "comments": 5
        },
        "user": {
            "id": "http://www.producthunt.com/divjpatel",
            "name": "Divyansh Patel"
        }
    },
    {
        "id": 27,
        "post": {
            "votes": 44,
            "link": "/r/76a3ab0d2d/15147",
            "name": "Vandebron",
            "tagline": "Buy clean energy from the farmer.",
            "ph_url": "/posts/vandebron",
            "comments": 5
        },
        "user": {
            "id": "http://www.producthunt.com/boredelonmusk",
            "name": "Bored Elon Musk"
        }
    },
    {
        "id": 28,
        "post": {
            "votes": 24,
            "link": "/r/93d4a23edb/15166",
            "name": "Envoyer",
            "tagline": "Zero Downtime PHP Deployment",
            "ph_url": "/posts/envoyer",
            "comments": 0
        },
        "user": {
            "id": "http://www.producthunt.com/karlclement",
            "name": "Karl Clement"
        }
    },
    {
        "id": 29,
        "post": {
            "votes": 28,
            "link": "/r/926eef576a/15160",
            "name": "Sorrce",
            "tagline": "3 clicks. Crazy content. An app to look at fun stuff",
            "ph_url": "/posts/sorrce",
            "comments": 1
        },
        "user": {
            "id": "http://www.producthunt.com/imkevinxu",
            "name": "Kevin Xu"
        }
    },
    {
        "id": 30,
        "post": {
            "votes": 21,
            "link": "/r/23a27d5e12/15141",
            "name": "mySugr Importer",
            "tagline": "Scan your blood sugar values directly from your BG meter",
            "ph_url": "/posts/mysugr-importer",
            "comments": 1
        },
        "user": {
            "id": "http://www.producthunt.com/andreaspizsa",
            "name": "Andreas Pizsa"
        }
    },
    {
        "id": 31,
        "post": {
            "votes": 18,
            "link": "/r/644317c972/15170",
            "name": "Asthma Health",
            "tagline": "Asthma Mobile Health study via ResearchKit ",
            "ph_url": "/posts/asthma-health",
            "comments": 1
        },
        "user": {
            "id": "http://www.producthunt.com/dshan",
            "name": "Derek Shanahan"
        }
    },
    {
        "id": 32,
        "post": {
            "votes": 18,
            "link": "/r/a04e76a8e8/15168",
            "name": "Alarm ",
            "tagline": "Connected home security platform that works with Apple Watch",
            "ph_url": "/posts/alarm",
            "comments": 0
        },
        "user": {
            "id": "http://www.producthunt.com/emmanuelamber",
            "name": "Emmanuel Amberber"
        }
    },
    {
        "id": 33,
        "post": {
            "votes": 16,
            "link": "/r/549cbaab68/15172",
            "name": "Lukla Endeavour",
            "tagline": "Thin winter outerwear made with space suit insulation",
            "ph_url": "/posts/lukla-endeavour",
            "comments": 0
        },
        "user": {
            "id": "http://www.producthunt.com/andyfortson",
            "name": "Andy Fortson"
        }
    },
    {
        "id": 34,
        "post": {
            "votes": 14,
            "link": "/r/73d7e2f240/15173",
            "name": "Touchtalent",
            "tagline": "Social network for creative people",
            "ph_url": "/posts/touchtalent",
            "comments": 1
        },
        "user": {
            "id": "http://www.producthunt.com/misbahspeaks",
            "name": "Misbah Ashraf"
        }
    },
    {
        "id": 35,
        "post": {
            "votes": 142,
            "link": "/r/2f2a0e373c/15142",
            "name": "The \"South By\" Guides",
            "tagline": "Find the best places and artists at SXSW15",
            "ph_url": "/posts/the-south-by-guides",
            "comments": 1
        },
        "user": {
            "id": "http://www.producthunt.com/adrianleb",
            "name": "Adrian Le Bas"
        }
    },
    {
        "id": 36,
        "post": {
            "votes": 11,
            "link": "/r/db36d116fb/15169",
            "name": "MyHeart Counts",
            "tagline": "Improve our understanding of heart health via ResearchKit",
            "ph_url": "/posts/myheart-counts",
            "comments": 1
        },
        "user": {
            "id": "http://www.producthunt.com/dshan",
            "name": "Derek Shanahan"
        }
    },
    {
        "id": 37,
        "post": {
            "votes": 8,
            "link": "/r/d9552def3e/15162",
            "name": "Dive in Deck",
            "tagline": "Cards to Ignite + Inspire Deeper Dialogue (Pre-order)",
            "ph_url": "/posts/dive-in-deck",
            "comments": 1
        },
        "user": {
            "id": "http://www.producthunt.com/chrismessina",
            "name": "Chris Messina ☠"
        }
    }
]