[
  {
    "id": 15385,
    "post": {
      "votes": 524,
      "link": "http://designresearchtechniques.com/?ref=phnest.in",
      "name": "Design Research Technique",
      "tagline": "Huge repository of design techniques for every project stage",
      "ph_url": "http://designresearchtechniques.com/?ref=phnest.in",
      "comments": 3
    },
    "user": {
      "id": "erictwillis",
      "image": "https://ph-avatars.imgix.net/16056/original?auto=format&fit=crop&crop=faces&w=160&h=160",
      "twitter": "erictwillis",
      "name": "Eric Willis",
      "tagline": "Mod @Product Hunt/ Founder @Chatmunk"
    }
  },
  {
    "id": 15388,
    "post": {
      "votes": 511,
      "link": "http://launchingnext.com/?ref=phnest.in",
      "name": "Launching Next",
      "tagline": "Showcasing the world's most promising new startups every day",
      "ph_url": "http://launchingnext.com/?ref=phnest.in",
      "comments": 19
    },
    "user": {
      "id": "_jacksmith",
      "image": "https://ph-avatars.imgix.net/962/original?auto=format&fit=crop&crop=faces&w=160&h=160",
      "twitter": "_jacksmith",
      "name": "Jack Smith",
      "tagline": "Serial Entrepreneur & Startup Adviser"
    }
  },
  {
    "id": 15386,
    "post": {
      "votes": 191,
      "link": "http://verifyapp.com/?ref=phnest.in",
      "name": "Verify",
      "tagline": "Test out ideas before you implement them.",
      "ph_url": "http://verifyapp.com/?ref=phnest.in",
      "comments": 1
    },
    "user": {
      "id": "_jacksmith",
      "image": "https://ph-avatars.imgix.net/962/original?auto=format&fit=crop&crop=faces&w=160&h=160",
      "twitter": "_jacksmith",
      "name": "Jack Smith",
      "tagline": "Serial Entrepreneur & Startup Adviser"
    }
  },
  {
    "id": 15391,
    "post": {
      "votes": 177,
      "link": "http://gethushbook.com/?ref=phnest.in",
      "name": "Hushbook",
      "tagline": "Tinder for unfriending on Facebook",
      "ph_url": "http://gethushbook.com/?ref=phnest.in",
      "comments": 23
    },
    "user": {
      "id": "_willfalcon",
      "image": "https://ph-avatars.imgix.net/172820/original?auto=format&fit=crop&crop=faces&w=160&h=160",
      "twitter": "_willfalcon",
      "name": "William Falcon",
      "tagline": "Dev, Co-Founder, HAC Studios"
    }
  },
  {
    "id": 15382,
    "post": {
      "votes": 199,
      "link": "http://scrapelogo.com/?ref=phnest.in",
      "name": "ScrapeLogo",
      "tagline": "Get logos for site/app with this dead-simple HTML API",
      "ph_url": "http://scrapelogo.com/?ref=phnest.in",
      "comments": 11
    },
    "user": {
      "id": "dilthemd",
      "image": "https://ph-avatars.imgix.net/1805/original?auto=format&fit=crop&crop=faces&w=160&h=160",
      "twitter": "dilthemd",
      "name": "Dil-Dominé Leonares ",
      "tagline": "Founder, Hyroglyphic Studios + Dcrypt"
    }
  },
  {
    "id": 15378,
    "post": {
      "votes": 128,
      "link": "http://writersmob.com?ref=phnest.in",
      "name": "Writersmob",
      "tagline": "Get a new writing prompt in your inbox and write everyday",
      "ph_url": "http://writersmob.com?ref=phnest.in",
      "comments": 4
    },
    "user": {
      "id": "choi_kl",
      "image": "https://ph-avatars.imgix.net/28983/original?auto=format&fit=crop&crop=faces&w=160&h=160",
      "twitter": "choi_kl",
      "name": "Kilim Choi",
      "tagline": "Engineer and Entrepreneur"
    }
  },
  {
    "id": 15387,
    "post": {
      "votes": 74,
      "link": "https://www.insitevr.com/?ref=phnest.in",
      "name": "Insite VR",
      "tagline": "The easiest way to view your 3D models in VR",
      "ph_url": "https://www.insitevr.com/?ref=phnest.in",
      "comments": 4
    },
    "user": {
      "id": "kwdinc",
      "image": "https://ph-avatars.imgix.net/79/original?auto=format&fit=crop&crop=faces&w=160&h=160",
      "twitter": "kwdinc",
      "name": "Kevin William David",
      "tagline": "Co-Founder, Sonder"
    }
  },
  {
    "id": 15383,
    "post": {
      "votes": 67,
      "link": "https://tosback.org/?ref=phnest.in",
      "name": "TOSBack",
      "tagline": "Terms-of-service tracker",
      "ph_url": "https://tosback.org/?ref=phnest.in",
      "comments": 1
    },
    "user": {
      "id": "chrismessina",
      "image": "https://ph-avatars.imgix.net/18280/original?auto=format&fit=crop&crop=faces&w=160&h=160",
      "twitter": "chrismessina",
      "name": "Chris Messina ✁_____",
      "tagline": "Developer Experience Lead at @Uber"
    }
  },
  {
    "id": 15389,
    "post": {
      "votes": 70,
      "link": "http://www.thepixelstick.com/?ref=phnest.in",
      "name": "PixelStick",
      "tagline": "create incredible light paintings using the pixelstick! ",
      "ph_url": "http://www.thepixelstick.com/?ref=phnest.in",
      "comments": 2
    },
    "user": {
      "id": "_camilletaylor",
      "image": "https://ph-avatars.imgix.net/36948/original?auto=format&fit=crop&crop=faces&w=160&h=160",
      "twitter": "_camilletaylor",
      "name": "Camille Taylor",
      "tagline": ""
    }
  },
  {
    "id": 15384,
    "post": {
      "votes": 52,
      "link": "https://www.docracy.com/tos/changes?ref=phnest.in",
      "name": "Docracy ToS Tracker ",
      "tagline": "Tracks TOS and privacy policies the world's top sites",
      "ph_url": "https://www.docracy.com/tos/changes?ref=phnest.in",
      "comments": 0
    },
    "user": {
      "id": "chrismessina",
      "image": "https://ph-avatars.imgix.net/18280/original?auto=format&fit=crop&crop=faces&w=160&h=160",
      "twitter": "chrismessina",
      "name": "Chris Messina ✁_____",
      "tagline": "Developer Experience Lead at @Uber"
    }
  },
  {
    "id": 15380,
    "post": {
      "votes": 42,
      "link": "https://tasketch.com?ref=phnest.in",
      "name": "Tasketch",
      "tagline": "Project management for scrum teams",
      "ph_url": "https://tasketch.com?ref=phnest.in",
      "comments": 4
    },
    "user": {
      "id": "violetanedkova",
      "image": "https://ph-avatars.imgix.net/9782/original?auto=format&fit=crop&crop=faces&w=160&h=160",
      "twitter": "violetanedkova",
      "name": "Violeta Nedkova",
      "tagline": "Marketing Coach Extraordinaire "
    }
  },
  {
    "id": 15390,
    "post": {
      "votes": 47,
      "link": "http://www.misprintedtype.com/fonts/comercial/?ref=phnest.in",
      "name": "Misprinted Type Fonts",
      "tagline": "Very beautiful fonts by Eduardo Recife",
      "ph_url": "http://www.misprintedtype.com/fonts/comercial/?ref=phnest.in",
      "comments": 1
    },
    "user": {
      "id": "_camilletaylor",
      "image": "https://ph-avatars.imgix.net/36948/original?auto=format&fit=crop&crop=faces&w=160&h=160",
      "twitter": "_camilletaylor",
      "name": "Camille Taylor",
      "tagline": ""
    }
  },
  {
    "id": 15392,
    "post": {
      "votes": 41,
      "link": "http://weekly.hatnote.com/?ref=phnest.in",
      "name": "Weeklypedia",
      "tagline": "Weekly email of the top 20 Wikipedia entries by # edits",
      "ph_url": "http://weekly.hatnote.com/?ref=phnest.in",
      "comments": 1
    },
    "user": {
      "id": "staringispolite",
      "image": "https://ph-avatars.imgix.net/146/original?auto=format&fit=crop&crop=faces&w=160&h=160",
      "twitter": "staringispolite",
      "name": "Jonathan Howard",
      "tagline": "Cofounder, Emissary"
    }
  },
  {
    "id": 15393,
    "post": {
      "votes": 21,
      "link": "http://droid.ly/?ref=phnest.in",
      "name": "Androidly",
      "tagline": "Your world on your wrist.",
      "ph_url": "http://droid.ly/?ref=phnest.in",
      "comments": 7
    },
    "user": {
      "id": "misbahspeaks",
      "image": "https://ph-avatars.imgix.net/37580/original?auto=format&fit=crop&crop=faces&w=160&h=160",
      "twitter": "misbahspeaks",
      "name": "Misbah Ashraf",
      "tagline": "Head of Product and Growth @keygoapp "
    }
  }
]