[
    {
        "id": 1,
        "post": {
            "votes": 28,
            "link": "/l/05cc48870e",
            "name": "Kidpreneurs",
            "tagline": "Entrepreneurship for kids 6-12 years old"
        }
    },
    {
        "id": 2,
        "post": {
            "votes": 27,
            "link": "/l/32dd7d8d71",
            "name": "Paperkit",
            "tagline": "Create and download custom graph, lined, or dot grid paper"
        }
    },
    {
        "id": 3,
        "post": {
            "votes": 21,
            "link": "/l/c9fda4b86b",
            "name": "Qolor",
            "tagline": "Fast and fun color grabber for iOS"
        }
    },
    {
        "id": 4,
        "post": {
            "votes": 11,
            "link": "/l/1762b81515",
            "name": "PencilCase",
            "tagline": "Transform your designs into native iOS apps in a heartbeat."
        }
    },
    {
        "id": 5,
        "post": {
            "votes": 8,
            "link": "/l/6321b59aca",
            "name": "Migraine Buddy (iOS)",
            "tagline": "1st crowdsourced migraine app comes to iOS"
        }
    },
    {
        "id": 6,
        "post": {
            "votes": 3,
            "link": "/l/bdad15196a",
            "name": "Tempo",
            "tagline": "Ultimate app to combine slow-mo &amp; timelapse"
        }
    },
    {
        "id": 7,
        "post": {
            "votes": 1,
            "link": "/l/6288ae3828",
            "name": "Ngenic",
            "tagline": "The Google Nest of Scandinavia"
        }
    }
]